jitxlib/voltage_divider/__init__.py
jitxlib/voltage_divider/circuit.py
jitxlib/voltage_divider/constraints.py
jitxlib/voltage_divider/errors.py
jitxlib/voltage_divider/inverse.py
jitxlib/voltage_divider/settings.py
jitxlib/voltage_divider/solver.py
jitxlib_voltage_divider-1.0.0.dist-info/METADATA
jitxlib_voltage_divider-1.0.0.dist-info/WHEEL
jitxlib_voltage_divider-1.0.0.dist-info/RECORD
