Metadata-Version: 2.4
Name: jitxlib-voltage-divider
Version: 1.0.0
Summary: JITX Voltage Divider Solver
Project-URL: Homepage, https://jitx.com
Project-URL: Documentation, https://docs.jitx.com
Author: JITX
Maintainer: JITX
Keywords: jitx,pcb,voltage divider
Classifier: Development Status :: 1 - Planning
Classifier: Framework :: Hatch
Classifier: Framework :: Pytest
Classifier: Intended Audience :: Developers
Classifier: License :: Other/Proprietary License
Classifier: Operating System :: OS Independent
Classifier: Programming Language :: Python
Classifier: Programming Language :: Python :: 3 :: Only
Classifier: Programming Language :: Python :: 3.12
Classifier: Programming Language :: Python :: 3.13
Classifier: Topic :: Scientific/Engineering :: Electronic Design Automation (EDA)
Classifier: Topic :: Software Development :: Libraries :: Python Modules
Classifier: Typing :: Typed
Requires-Python: >=3.12
Requires-Dist: jitx<5,>=4.0.0
Requires-Dist: jitxlib-parts<2,>=1.0.0
